sphinxcontrib/packages/__init__.py
sphinxcontrib_packages-1.2.0.dist-info/AUTHORS
sphinxcontrib_packages-1.2.0.dist-info/LICENSE
sphinxcontrib_packages-1.2.0.dist-info/METADATA
sphinxcontrib_packages-1.2.0.dist-info/WHEEL
sphinxcontrib_packages-1.2.0.dist-info/top_level.txt
sphinxcontrib_packages-1.2.0.dist-info/zip-safe
sphinxcontrib_packages-1.2.0.dist-info/RECORD
