Metadata-Version: 2.1
Name: sphinxcontrib-packages
Version: 1.2.0
Summary: This packages contains the Packages sphinx extension, which provides directives to display packages installed on the host machine
Home-page: https://framagit.org/spalax/sphinxcontrib-packages
Author: Louis Paternault
Author-email: spalax@gresille.org
License: AGPLv3 or any later version
Project-URL: Documentation, http://packages.readthedocs.io
Project-URL: Source, https://framagit.org/spalax/sphinxcontrib-packages
Project-URL: Tracker, https://framagit.org/spalax/sphinxcontrib-packages/issues
Keywords: sphinx package system
Classifier: Development Status :: 5 - Production/Stable
Classifier: Framework :: Sphinx :: Extension
Classifier: Intended Audience :: Developers
Classifier: Intended Audience :: System Administrators
Classifier: License :: OSI Approved :: GNU Affero General Public License v3 or later (AGPLv3+)
Classifier: Operating System :: Unix
Classifier: Programming Language :: Python :: 3
Classifier: Programming Language :: Python :: 3.8
Classifier: Programming Language :: Python :: 3.9
Classifier: Programming Language :: Python :: 3.10
Classifier: Programming Language :: Python :: 3.11
Classifier: Programming Language :: Python :: 3.12
Classifier: Programming Language :: Python :: 3.13
Classifier: Topic :: Documentation :: Sphinx
Classifier: Topic :: Software Development :: Libraries :: Python Modules
Requires-Python: <4,>=3.8
License-File: LICENSE
License-File: AUTHORS
Requires-Dist: distro
Requires-Dist: sphinx
